fyamaktestpypi/__init__.py
fyamaktestpypi/statistics.py
fyamaktestpypi-0.0.1.dist-info/LICENSE
fyamaktestpypi-0.0.1.dist-info/METADATA
fyamaktestpypi-0.0.1.dist-info/WHEEL
fyamaktestpypi-0.0.1.dist-info/top_level.txt
fyamaktestpypi-0.0.1.dist-info/RECORD
