Metadata-Version: 2.1
Name: fyamaktestpypi
Version: 0.0.1
Summary: A simple package for calculating statistics.
Author-email: Furkan Yamak <furkanyamaak@gmail.com>
Project-URL: Homepage, https://github.com/f-yamak/fyamaktestpypi
Keywords: fyamak,statistics
Classifier: Development Status :: 3 - Alpha
Classifier: Intended Audience :: Developers
Classifier: License :: OSI Approved :: MIT License
Classifier: Programming Language :: Python :: 3
Classifier: Operating System :: OS Independent
Requires-Python: >=3.6.0
License-File: LICENSE
